BetterPick/__init__.py
better_pick-1.2.dist-info/LICENSE
better_pick-1.2.dist-info/METADATA
better_pick-1.2.dist-info/WHEEL
better_pick-1.2.dist-info/top_level.txt
better_pick-1.2.dist-info/RECORD
