Metadata-Version: 2.1
Name: better_pick
Version: 1.2
Summary: Modern menu selection in command prompt for command lines app!
Home-page: https://github.com/ScadeBlock/BetterPick
Author: ScadeBlock
Project-URL: Documentation, https://github.com/ScadeBlock/BetterPick
Project-URL: Bug Reports, https://github.com/ScadeBlock/BetterPick/issues
Project-URL: Source Code, https://github.com/ScadeBlock/BetterPick
Keywords: pick,menu,select,command prompt,command lines
Classifier: Development Status :: 5 - Production/Stable
Classifier: Intended Audience :: Developers
Classifier: Topic :: Software Development :: Build Tools
Classifier: Programming Language :: Python :: 3
Classifier: Programming Language :: Python :: 3.6
Classifier: Programming Language :: Python :: 3.7
Classifier: Programming Language :: Python :: 3.8
Classifier: Programming Language :: Python :: 3.9
Classifier: Programming Language :: Python :: 3 :: Only
Classifier: License :: OSI Approved :: MIT License
Classifier: Operating System :: OS Independent
Requires-Python: >=3.6
License-File: LICENSE
Requires-Dist: colorama
Requires-Dist: keyboard
Provides-Extra: dev
Requires-Dist: check-manifest ; extra == 'dev'
